middleware_service/__init__.py
middleware_service/version.py
middleware_service/middleware/__init__.py
middleware_service/middleware/hmac_middleware.py
middleware_service/signatures/__init__.py
middleware_service/signatures/hmac_signature.py
middleware_service/signatures/secret_key_generator.py
middleware_service/signatures/signature_validation.py
middleware_service-0.1.1.dist-info/LICENCE
middleware_service-0.1.1.dist-info/METADATA
middleware_service-0.1.1.dist-info/WHEEL
middleware_service-0.1.1.dist-info/top_level.txt
middleware_service-0.1.1.dist-info/RECORD
