Metadata-Version: 2.1
Name: middleware-service
Version: 0.1.1
Summary: for data authentication by middleware
Home-page: https://github.com/gupta24/service
Author: Rahul
Author-email: rahul.gupta@adcuratio.com
License: MIT
Project-URL: Bug Tracker, https://github.com/gupta24/service/issues
Platform: UNKNOWN
Classifier: Programming Language :: Python :: 3
Classifier: License :: OSI Approved :: MIT License
Classifier: Operating System :: OS Independent
License-File: LICENCE
Requires-Dist: fastapi
Requires-Dist: uvicorn
Requires-Dist: sqlalchemy
Requires-Dist: fastapi-utils
Requires-Dist: requests
Requires-Dist: psycopg2-binary
Requires-Dist: starlette
Requires-Dist: python-dotenv
